rklib/__init__.py
rklib/address.py
rklib/assets.py
rklib/block.py
rklib/blockchain.py
rklib/permissions.py
rklib/stream.py
rklib/transaction.py
rklib/wallet.py
rklib/test/__init__.py
rklib/test/test_address.py
rklib/test/test_assets.py
rklib/test/test_block.py
rklib/test/test_blockchain.py
rklib/test/test_permissions.py
rklib/test/test_stream.py
rklib/test/test_transaction.py
rklib/test/test_wallet.py
rklib-0.1.0.dist-info/DESCRIPTION.rst
rklib-0.1.0.dist-info/METADATA
rklib-0.1.0.dist-info/RECORD
rklib-0.1.0.dist-info/WHEEL
rklib-0.1.0.dist-info/metadata.json
rklib-0.1.0.dist-info/top_level.txt
